kod_normalize/__init__.py
kod_normalize/normalize.py
tests/__init__.py
tests/test.py
kod_norm_str-0.3.1.dist-info/LICENSE
kod_norm_str-0.3.1.dist-info/METADATA
kod_norm_str-0.3.1.dist-info/WHEEL
kod_norm_str-0.3.1.dist-info/top_level.txt
kod_norm_str-0.3.1.dist-info/RECORD
