Metadata-Version: 2.1
Name: kod-norm-str
Version: 0.3.1
Summary: A package for normalizing and generating a unique identifier of strings. Great for when you need to search for exact matches.
Home-page: https://github.com/kod3000/kod-normalize-str
Author: Nestor Rivera
Author-email: kod3000@gmail.com
Classifier: Programming Language :: Python :: 3
Classifier: License :: OSI Approved :: MIT License
Classifier: Operating System :: OS Independent
Requires-Python: >=3.6
License-File: LICENSE
